pandas_emetrics/__init__.py
pandas_emetrics/metrics/__init__.py
pandas_emetrics/metrics/k_anonymity.py
pandas_emetrics/metrics/l_diversity.py
pandas_emetrics/processing/__init__.py
pandas_emetrics/processing/diff_privacy.py
pandas_emetrics/processing/k_anonymize.py
pandas_emetrics/processing/suppress.py
pandas_emetrics-1.0.0.dist-info/METADATA
pandas_emetrics-1.0.0.dist-info/WHEEL
pandas_emetrics-1.0.0.dist-info/licenses/LICENSE
pandas_emetrics-1.0.0.dist-info/RECORD
