Metadata-Version: 2.4
Name: pandas_emetrics
Version: 1.0.0
Summary: A Python package integrating ethical considerations into Pandas DataFrame processing.
Project-URL: Documentation, https://github.com/nkasica/pandas-emetrics/wiki/User-Guide
Project-URL: Repository, https://github.com/nkasica/pandas-emetrics
Project-URL: Issues, https://github.com/nkasica/pandas-emetrics/issues
Author-email: Noah Kasica <nkasica21@gmail.com>
Maintainer-email: Noah Kasica <nkasica21@gmail.com>
License-File: LICENSE
Keywords: data science,ethics,numpy,pandas,python3
Classifier: Development Status :: 5 - Production/Stable
Classifier: Intended Audience :: Developers
Classifier: Intended Audience :: Education
Classifier: Intended Audience :: Healthcare Industry
Classifier: Intended Audience :: Science/Research
Classifier: License :: OSI Approved :: MIT License
Classifier: Natural Language :: English
Requires-Dist: numpy
Requires-Dist: pandas
Requires-Dist: pandas-flavor
